zql/__init__.py
zql-0.0.1.dist-info/WHEEL
zql-0.0.1.dist-info/METADATA
zql-0.0.1.dist-info/RECORD
